<?xml version="1.0" encoding="utf-8"?>
<XCExtension>
	<ProjectSections>
		<Extends>
$if(iOSExtensionLibraryMainInfo.InUseByMain)$
			<PBXBuildFile>
				<![CDATA[		494F00A1C0F442FD9BEF358B /* GXCoreModule_SD_RemoteConfig.xcframework in Frameworks */ = {isa = PBXBuildFile; fileRef = 494F00A2C0F442FD9BEF358B /* GXCoreModule_SD_RemoteConfig.xcframework */; };
				494F00A3C0F442FD9BEF358B /* GXCoreModule_SD_RemoteConfig.xcframework in Embed Frameworks */ = {isa = PBXBuildFile; fileRef = 494F00A2C0F442FD9BEF358B /* GXCoreModule_SD_RemoteConfig.xcframework */; settings = {ATTRIBUTES = (CodeSignOnCopy, RemoveHeadersOnCopy, ); }; };
				]]>
			</PBXBuildFile>
			<PBXFrameworksBuildPhase>
				<![CDATA[				494F00A1C0F442FD9BEF358B /* GXCoreModule_SD_RemoteConfig.xcframework in Frameworks */,
				]]>
			</PBXFrameworksBuildPhase>
			<PBXCopyFilesBuildPhaseEmbedFrameworks>
				<![CDATA[				494F00A3C0F442FD9BEF358B /* GXCoreModule_SD_RemoteConfig.xcframework in Embed Frameworks */,
				]]>
			</PBXCopyFilesBuildPhaseEmbedFrameworks>
$endif$
$if(iOSExtensionLibraryMainInfo.InUseByWatchApp)$
			<PBXBuildFile>
				<![CDATA[		494F00A8C0F442FD9BEF358B /* GXCoreModule_SD_RemoteConfig.xcframework in Frameworks */ = {isa = PBXBuildFile; fileRef = 494F00A2C0F442FD9BEF358B /* GXCoreModule_SD_RemoteConfig.xcframework */; };
				494F00A9C0F442FD9BEF358B /* GXCoreModule_SD_RemoteConfig.xcframework in Embed Frameworks */ = {isa = PBXBuildFile; fileRef = 494F00A2C0F442FD9BEF358B /* GXCoreModule_SD_RemoteConfig.xcframework */; settings = {ATTRIBUTES = (CodeSignOnCopy, RemoveHeadersOnCopy, ); }; };
				]]>
			</PBXBuildFile>
			<PBXFrameworksBuildPhase target='WatchExtension'>
				<![CDATA[				494F00A8C0F442FD9BEF358B /* GXCoreModule_SD_RemoteConfig.xcframework in Frameworks */,
				]]>
			</PBXFrameworksBuildPhase>
			<PBXCopyFilesBuildPhaseEmbedFrameworks target='WatchExtension'>
				<![CDATA[				494F00A9C0F442FD9BEF358B /* GXCoreModule_SD_RemoteConfig.xcframework in Embed Frameworks */,
				]]>
			</PBXCopyFilesBuildPhaseEmbedFrameworks>
$endif$
			<PBXFileReference>
				<![CDATA[		494F00A2C0F442FD9BEF358B /* GXCoreModule_SD_RemoteConfig.xcframework */ = {isa = PBXFileReference; lastKnownFileType = wrapper.xcframework; name = GXCoreModule_SD_RemoteConfig.xcframework; path = "\$(USER_LIBRARY_DIR)/GeneXus/GeneXus/$Model.GenexusIDEVersionDir$/GXCoreModule_SD_RemoteConfig.xcframework"; sourceTree = SOURCE_ROOT; };
				]]>
			</PBXFileReference>
			<PBXGroup_EmbedFrameworks>
				<![CDATA[				494F00A2C0F442FD9BEF358B /* GXCoreModule_SD_RemoteConfig.xcframework */,
				]]>
			</PBXGroup_EmbedFrameworks>
		</Extends>
	</ProjectSections>
</XCExtension>
